{
  "stageName": "المرحلة الرابعة: تحديد القواعد القانونية المنطبقة",
  "description": "تحديد القواعد القانونية المنطبقة والمتطلبات القانونية المطلوبة في إطار النظام القانوني الفلسطيني",
  "key_points": [
    "تحديد القواعد القانونية المنطبقة في إطار القوانين الفلسطينية",
    "تحديد المتطلبات القانونية المطلوبة في إطار القوانين الفلسطينية",
    "تحديد القواعد القانونية الفلسطينية المتكررة",
    "تحديد المتطلبات القانونية الفلسطينية المتطرفة"
  ],
  "questions": [
    "ما هي القواعد القانونية المنطبقة التي يجب أن نفهمها؟",
    "ما هي المتطلبات القانونية المطلوبة التي يجب أن نفهمها؟",
    "ما هي القواعد القانونية الفلسطينية التي تظهر بشكل متكرر؟",
    "ما هي المتطلبات القانونية الفلسطينية التي تظهر بشكل متطرف؟"
  ],
  "examples": [
    "مثال: تحديد قواعد العقد في القانون المدني الفلسطيني",
    "مثال: تحديد متطلبات الإثبات في قانون الإجراءات المدنية"
  ],
  "legalReferences": [
    "القانون المدني الفلسطيني",
    "قانون الإجراءات المدنية الفلسطيني",
    "قانون الإثبات الفلسطيني"
  ],
  "complexity": "intermediate"
} 